boondh
