Metadata-Version: 2.1
Name: boondh
Version: 0.1.5
Summary: A Swiss Knife
Home-page: https://github.com/rohit-mehra/boondh
Author: Rohit Mehra
Author-email: iirohitmehra@gmail.com
License: UNKNOWN
Keywords: utility,data,multiprocessing,cli,tools
Platform: UNKNOWN
Classifier: Development Status :: 3 - Alpha
Classifier: Intended Audience :: Developers
Classifier: License :: OSI Approved :: MIT License
Classifier: Operating System :: OS Independent
Classifier: Programming Language :: Python :: 3
Classifier: Programming Language :: Python :: 3.6
Classifier: Programming Language :: Python :: 3.7
Classifier: Topic :: Software Development
Requires-Python: >=3.6.0
